klickbrick_codeangler/__init__.py
klickbrick_codeangler/main.py
klickbrick_codeangler-0.1.3.dist-info/entry_points.txt
klickbrick_codeangler-0.1.3.dist-info/LICENSE
klickbrick_codeangler-0.1.3.dist-info/WHEEL
klickbrick_codeangler-0.1.3.dist-info/METADATA
klickbrick_codeangler-0.1.3.dist-info/RECORD
